mcp_add/__init__.py
mcp_add/server.py
mcp_add-0.1.9.dist-info/METADATA
mcp_add-0.1.9.dist-info/WHEEL
mcp_add-0.1.9.dist-info/entry_points.txt
mcp_add-0.1.9.dist-info/top_level.txt
mcp_add-0.1.9.dist-info/RECORD
